brasil.gov.temas-2.0.3-py2.7-nspkg.pth
brasil/gov/temas/__init__.py
brasil/gov/temas/__init__.pyc
brasil/gov/temas/configure.zcml
brasil/gov/temas/testing.py
brasil/gov/temas/jbot/OFS.standard.favicon.ico
brasil/gov/temas/jbot/Products.CMFPlone.skins.plone_login.login_form.cpt
brasil/gov/temas/tests/__init__.py
brasil/gov/temas/tests/test_acessibilidade.py
brasil/gov/temas/tests/test_setup.py
brasil/gov/temas/tests/tests_funcionais.py
brasil/gov/temas/themes/README.rst
brasil/gov/temas/themes/branco/brasilgovtemas-b582c40.css
brasil/gov/temas/themes/branco/brasilgovtemas-b582c40.js
brasil/gov/temas/themes/branco/index-minimalista.html
brasil/gov/temas/themes/branco/index.html
brasil/gov/temas/themes/branco/manifest.cfg
brasil/gov/temas/themes/branco/preview.png
brasil/gov/temas/themes/branco/rules.xml
brasil/gov/temas/themes/branco/favicons/android-chrome-192x192.png
brasil/gov/temas/themes/branco/favicons/android-chrome-512x512.png
brasil/gov/temas/themes/branco/favicons/apple-touch-icon.png
brasil/gov/temas/themes/branco/favicons/browserconfig.xml
brasil/gov/temas/themes/branco/favicons/favicon-16x16.png
brasil/gov/temas/themes/branco/favicons/favicon-32x32.png
brasil/gov/temas/themes/branco/favicons/manifest.json
brasil/gov/temas/themes/branco/favicons/mstile-150x150.png
brasil/gov/temas/themes/branco/favicons/safari-pinned-tab.svg
brasil/gov/temas/themes/branco/fonts/Raleway-Black.eot
brasil/gov/temas/themes/branco/fonts/Raleway-Black.svg
brasil/gov/temas/themes/branco/fonts/Raleway-Black.ttf
brasil/gov/temas/themes/branco/fonts/Raleway-Black.woff
brasil/gov/temas/themes/branco/fonts/Raleway-Black.woff2
brasil/gov/temas/themes/branco/fonts/Raleway-Bold.eot
brasil/gov/temas/themes/branco/fonts/Raleway-Bold.svg
brasil/gov/temas/themes/branco/fonts/Raleway-Bold.ttf
brasil/gov/temas/themes/branco/fonts/Raleway-Bold.woff
brasil/gov/temas/themes/branco/fonts/Raleway-Bold.woff2
brasil/gov/temas/themes/branco/fonts/Raleway-Extrabold.eot
brasil.gov.temas-2.0.3.dist-info/METADATA
brasil.gov.temas-2.0.3.dist-info/WHEEL
brasil.gov.temas-2.0.3.dist-info/entry_points.txt
brasil.gov.temas-2.0.3.dist-info/namespace_packages.txt
brasil.gov.temas-2.0.3.dist-info/top_level.txt
brasil.gov.temas-2.0.3.dist-info/RECORD
