Metadata-Version: 2.1
Name: brasil.gov.temas
Version: 2.0.3
Summary: Temas para o Portal Padrao do Governo Federal
Home-page: https://github.com/plonegovbr/brasil.gov.temas
Author: PloneGov.BR
Author-email: gov@plone.org.br
License: GPLv2
Keywords: diazo theme
Platform: UNKNOWN
Classifier: Development Status :: 5 - Production/Stable
Classifier: Environment :: Web Environment
Classifier: Framework :: Plone
Classifier: Framework :: Plone :: 4.3
Classifier: Intended Audience :: Developers
Classifier: Intended Audience :: System Administrators
Classifier: License :: OSI Approved :: GNU General Public License v2 (GPLv2)
Classifier: Operating System :: OS Independent
Classifier: Programming Language :: Python
Classifier: Programming Language :: Python :: 2.7
Classifier: Topic :: Internet :: WWW/HTTP
Classifier: Topic :: Internet :: WWW/HTTP :: Dynamic Content
Classifier: Topic :: Software Development :: Libraries :: Python Modules
Requires-Dist: brasil.gov.portal
Requires-Dist: plone.app.themingplugins
Requires-Dist: plone.resource
Requires-Dist: Products.CMFPlone (>=4.3)
Requires-Dist: setuptools
Provides-Extra: test
Requires-Dist: plone.app.testing ; extra == 'test'
Requires-Dist: plone.app.theming ; extra == 'test'
Requires-Dist: plone.registry ; extra == 'test'
Requires-Dist: plone.testing ; extra == 'test'
Requires-Dist: transaction ; extra == 'test'
Requires-Dist: zope.component ; extra == 'test'
